{
  "buttons": [
    [
      {
        "action": {
          "type": "text",
          "label": "\uD83D\uDDE1Атака\uD83D\uDDE1",
          "payload": ""
        },
        "color": "secondary"
      }
    ],
    [
      {
        "action": {
          "type": "text",
          "label": "\uD83D\uDEE1Блок\uD83D\uDEE1",
          "payload": ""
        },
        "color": "secondary"
      }
    ],
    [
      {
        "action": {
          "type": "text",
          "label": "\uD83E\uDDB6Сбежать\uD83E\uDDB6",
          "payload": ""
        },
        "color": "secondary"
      }
    ],
    [
      {
        "action": {
          "type": "text",
          "label": "\uD83D\uDCBCИнвентарь\uD83D\uDCBC",
          "payload": ""
        },
        "color": "secondary"
      }
    ]
  ],


  "inline": true
}